dpd_ai_chatbot_julia_stats_client-0.2.5.dist-info/METADATA
dpd_ai_chatbot_julia_stats_client-0.2.5.dist-info/WHEEL
dpd_ai_chatbot_julia_stats_client/__init__.py
dpd_ai_chatbot_julia_stats_client/client.py
dpd_ai_chatbot_julia_stats_client/models.py
dpd_ai_chatbot_julia_stats_client-0.2.5.dist-info/RECORD
