Metadata-Version: 2.1
Name: dpd-ai-chatbot-julia-stats-client
Version: 0.2.5
Summary: Client for dpd-ai-chatbot-julia-stats-api
Author-Email: bbilskiy <bbilskiy0266@smartds.ru>
License: MIT
Requires-Python: >=3.9.2
Requires-Dist: pydantic>=2.9.1
Requires-Dist: pytest>=8.3.3
Requires-Dist: aiohttp>=3.10.5
